lsassy/__init__.py
lsassy/console.py
lsassy/core.py
lsassy/credential.py
lsassy/dumper.py
lsassy/impacketfile.py
lsassy/logger.py
lsassy/parser.py
lsassy/session.py
lsassy/utils.py
lsassy/writer.py
lsassy/dumpmethod/__init__.py
lsassy/dumpmethod/comsvcs.py
lsassy/dumpmethod/comsvcs_stealth.py
lsassy/dumpmethod/dllinject.py
lsassy/dumpmethod/dumpert.py
lsassy/dumpmethod/dumpertdll.py
lsassy/dumpmethod/edrsandblast.py
lsassy/dumpmethod/mirrordump.py
lsassy/dumpmethod/mirrordump_embedded.py
lsassy/dumpmethod/nanodump.py
lsassy/dumpmethod/nanodump_ssp_embedded.py
lsassy/dumpmethod/ppldump.py
lsassy/dumpmethod/ppldump_embedded.py
lsassy/dumpmethod/procdump.py
lsassy/dumpmethod/procdump_embedded.py
lsassy/dumpmethod/rawrpc.py
lsassy/dumpmethod/rawrpc_embedded.py
lsassy/dumpmethod/rdrleakdiag.py
lsassy/dumpmethod/silentprocessexit.py
lsassy/dumpmethod/sqldumper.py
lsassy/dumpmethod/wer.py
lsassy/exec/__init__.py
lsassy/exec/mmc.py
lsassy/exec/smb.py
lsassy/exec/smb_stealth.py
lsassy/exec/task.py
lsassy/exec/wmi.py
lsassy/output/__init__.py
lsassy/output/grep_output.py
lsassy/output/json_output.py
lsassy/output/pretty_output.py
lsassy/output/table_output.py
lsassy-3.1.15.dist-info/licenses/LICENSE
lsassy-3.1.15.dist-info/METADATA
lsassy-3.1.15.dist-info/WHEEL
lsassy-3.1.15.dist-info/entry_points.txt
lsassy-3.1.15.dist-info/top_level.txt
lsassy-3.1.15.dist-info/zip-safe
lsassy-3.1.15.dist-info/RECORD
