Metadata-Version: 2.4
Name: lsassy
Version: 3.1.15
Summary: Python library to extract credentials from lsass remotely
Home-page: https://github.com/Hackndo/lsassy/
Author: Pixis
Author-email: pixis <pixis@hackndo.com>
License: MIT
Requires-Python: >=3.6
License-File: LICENSE
Requires-Dist: impacket>=0.11.0
Requires-Dist: netaddr>=1.3.0
Requires-Dist: pypykatz>=0.6.9
Requires-Dist: rich>=13.7.1
Provides-Extra: dev
Requires-Dist: ruff>=0.5.1; extra == "dev"
Requires-Dist: pre-commit>=3.7.1; extra == "dev"
Dynamic: author
Dynamic: home-page
Dynamic: license-file
Dynamic: requires-python
